hdijupyterutils/__init__.py
hdijupyterutils/configuration.py
hdijupyterutils/constants.py
hdijupyterutils/events.py
hdijupyterutils/eventshandler.py
hdijupyterutils/filehandler.py
hdijupyterutils/filesystemreaderwriter.py
hdijupyterutils/guid.py
hdijupyterutils/ipythondisplay.py
hdijupyterutils/ipywidgetfactory.py
hdijupyterutils/log.py
hdijupyterutils/utils.py
vnpt_hdijupyterutils-0.1.1.dist-info/LICENSE.md
vnpt_hdijupyterutils-0.1.1.dist-info/METADATA
vnpt_hdijupyterutils-0.1.1.dist-info/WHEEL
vnpt_hdijupyterutils-0.1.1.dist-info/top_level.txt
vnpt_hdijupyterutils-0.1.1.dist-info/RECORD
