Metadata-Version: 2.1
Name: vnpt-hdijupyterutils
Version: 0.1.1
Summary: HdiJupyterUtils: Utils for Jupyter projects from HDInsight team
Home-page: https://github.com/jupyter-incubator/sparkmagic
Download-URL: https://github.com/jupyter-incubator/sparkmagic
Author: Jupyter Development Team
Author-email: jupyter@googlegroups.org
License: BSD 3-clause
Classifier: Development Status :: 4 - Beta
Classifier: Environment :: Console
Classifier: Intended Audience :: Science/Research
Classifier: License :: OSI Approved :: BSD License
Classifier: Natural Language :: English
Classifier: Programming Language :: Python :: 3.7
License-File: LICENSE.md
Requires-Dist: ipython>=4.0.2
Requires-Dist: ipywidgets>5.0.0
Requires-Dist: ipykernel>=4.2.2
Requires-Dist: jupyter>=1
Requires-Dist: pandas<3.0.0
Requires-Dist: numpy>=1.16.5
Requires-Dist: notebook>=4.2
